django_create/__init__.py
django_create/cli.py
django_create/commands/__init__.py
django_create/commands/create_model.py
django_create/commands/create_serializer.py
django_create/commands/create_test.py
django_create/commands/create_view.py
django_create/commands/create_viewset.py
django_create/commands/folderize_app.py
django_create/templates/__init__.py
django_create/templates/model_template.txt
django_create/templates/model_template_no_import.txt
django_create/templates/serializer_template.txt
django_create/templates/serializer_template_no_import.txt
django_create/templates/test_template.txt
django_create/templates/test_template_no_import.txt
django_create/templates/view_template.txt
django_create/templates/view_template_no_import.txt
django_create/templates/viewset_template.txt
django_create/templates/viewset_template_no_import.txt
django_create/utils.py
django_create-0.1.4.dist-info/entry_points.txt
django_create-0.1.4.dist-info/LICENSE
django_create-0.1.4.dist-info/METADATA
django_create-0.1.4.dist-info/WHEEL
django_create-0.1.4.dist-info/RECORD
