Metadata-Version: 2.1
Name: django-create
Version: 0.1.4
Summary: A CLI tool to help Django developers create file templates.
License: MIT
Author: Jonathan Ribak
Author-email: yonch.baalil@gmail.com
Requires-Python: >=3.8,<4.0
Classifier: License :: OSI Approved :: MIT License
Classifier: Programming Language :: Python :: 3
Classifier: Programming Language :: Python :: 3.8
Classifier: Programming Language :: Python :: 3.9
Classifier: Programming Language :: Python :: 3.10
Classifier: Programming Language :: Python :: 3.11
Requires-Dist: click (>=8.1,<9.0)
